{"expireTime":9007200867590241000,"key":"gatsby-plugin-mdx-entire-payload-927ee7d1f8be0d4a8cf8288bf517d57a-","val":{"mdast":{"type":"root","children":[{"type":"jsx","value":"<FullWidthImage src=\"https://res.cloudinary.com/dg3gyk0gu/image/upload/c_scale,w_1800/v1589145525/maggieappleton.com/pure-react/Cover.png\" />","position":{"start":{"line":2,"column":1,"offset":1},"end":{"line":2,"column":142,"offset":142},"indent":[]}},{"type":"jsx","value":"<Center>","position":{"start":{"line":4,"column":1,"offset":144},"end":{"line":4,"column":9,"offset":152},"indent":[]}},{"type":"heading","depth":2,"children":[{"type":"text","value":"Illustration & art direction for Dave Ceddia's ","position":{"start":{"line":6,"column":4,"offset":157},"end":{"line":6,"column":51,"offset":204},"indent":[]}},{"type":"jsx","value":"<a noTip href=\"https://purereact.com/\">","position":{"start":{"line":6,"column":51,"offset":204},"end":{"line":6,"column":90,"offset":243},"indent":[]}},{"type":"text","value":"Pure React","position":{"start":{"line":6,"column":90,"offset":243},"end":{"line":6,"column":100,"offset":253},"indent":[]}},{"type":"jsx","value":"</a>","position":{"start":{"line":6,"column":100,"offset":253},"end":{"line":6,"column":104,"offset":257},"indent":[]}},{"type":"text","value":" online course.","position":{"start":{"line":6,"column":104,"offset":257},"end":{"line":6,"column":119,"offset":272},"indent":[]}}],"position":{"start":{"line":6,"column":1,"offset":154},"end":{"line":6,"column":119,"offset":272},"indent":[]}},{"type":"jsx","value":"<br />\n<br />","position":{"start":{"line":8,"column":1,"offset":274},"end":{"line":9,"column":7,"offset":287},"indent":[1]}},{"type":"jsx","value":"<BasicImage width=\"100px\" src=\"https://res.cloudinary.com/dg3gyk0gu/image/upload/c_scale,w_100/v1589145522/maggieappleton.com/pure-react/PR_LogoLarge_2x.png\" />","position":{"start":{"line":11,"column":1,"offset":289},"end":{"line":11,"column":161,"offset":449},"indent":[]}},{"type":"jsx","value":"</Center>","position":{"start":{"line":13,"column":1,"offset":451},"end":{"line":13,"column":10,"offset":460},"indent":[]}},{"type":"jsx","value":"<br />\n<br />","position":{"start":{"line":15,"column":1,"offset":462},"end":{"line":16,"column":7,"offset":475},"indent":[1]}},{"type":"jsx","value":"<FullWidth bgcolour=\"linear-gradient(#09AFFD, #2F70E4)\" >","position":{"start":{"line":18,"column":1,"offset":477},"end":{"line":18,"column":58,"offset":534},"indent":[]}},{"type":"jsx","value":"<BasicImage src=\"https://res.cloudinary.com/dg3gyk0gu/image/upload/c_scale,w_1000/v1589145523/maggieappleton.com/pure-react/Plant_Header.png\" />","position":{"start":{"line":20,"column":1,"offset":536},"end":{"line":20,"column":145,"offset":680},"indent":[]}},{"type":"jsx","value":"</FullWidth>","position":{"start":{"line":22,"column":1,"offset":682},"end":{"line":22,"column":13,"offset":694},"indent":[]}},{"type":"jsx","value":"<br/>","position":{"start":{"line":24,"column":1,"offset":696},"end":{"line":24,"column":6,"offset":701},"indent":[]}},{"type":"heading","depth":2,"children":[{"type":"text","value":"Module Illustrations","position":{"start":{"line":26,"column":4,"offset":706},"end":{"line":26,"column":24,"offset":726},"indent":[]}}],"position":{"start":{"line":26,"column":1,"offset":703},"end":{"line":26,"column":24,"offset":726},"indent":[]}},{"type":"paragraph","children":[{"type":"text","value":"The course is split into 9 modules, each focusing on a specific skill set like ","position":{"start":{"line":28,"column":1,"offset":728},"end":{"line":28,"column":80,"offset":807},"indent":[]}},{"type":"emphasis","children":[{"type":"text","value":"Modern JavaScript Essentials","position":{"start":{"line":28,"column":81,"offset":808},"end":{"line":28,"column":109,"offset":836},"indent":[]}}],"position":{"start":{"line":28,"column":80,"offset":807},"end":{"line":28,"column":110,"offset":837},"indent":[]}},{"type":"text","value":", ","position":{"start":{"line":28,"column":110,"offset":837},"end":{"line":28,"column":112,"offset":839},"indent":[]}},{"type":"emphasis","children":[{"type":"text","value":"API Requests,","position":{"start":{"line":28,"column":113,"offset":840},"end":{"line":28,"column":126,"offset":853},"indent":[]}}],"position":{"start":{"line":28,"column":112,"offset":839},"end":{"line":28,"column":127,"offset":854},"indent":[]}},{"type":"text","value":" and ","position":{"start":{"line":28,"column":127,"offset":854},"end":{"line":28,"column":132,"offset":859},"indent":[]}},{"type":"emphasis","children":[{"type":"text","value":"Context for Application State","position":{"start":{"line":28,"column":133,"offset":860},"end":{"line":28,"column":162,"offset":889},"indent":[]}}],"position":{"start":{"line":28,"column":132,"offset":859},"end":{"line":28,"column":163,"offset":890},"indent":[]}},{"type":"text","value":". ","position":{"start":{"line":28,"column":163,"offset":890},"end":{"line":28,"column":165,"offset":892},"indent":[]}}],"position":{"start":{"line":28,"column":1,"offset":728},"end":{"line":28,"column":165,"offset":892},"indent":[]}},{"type":"paragraph","children":[{"type":"text","value":"Each needed their own illustration, so I developed a unified shape language and colour palette to generate a variety of matching ones.","position":{"start":{"line":30,"column":1,"offset":894},"end":{"line":30,"column":135,"offset":1028},"indent":[]}}],"position":{"start":{"line":30,"column":1,"offset":894},"end":{"line":30,"column":135,"offset":1028},"indent":[]}},{"type":"jsx","value":"<br/>","position":{"start":{"line":32,"column":1,"offset":1030},"end":{"line":32,"column":6,"offset":1035},"indent":[]}},{"type":"jsx","value":"<ThreeImageGrid>","position":{"start":{"line":34,"column":1,"offset":1037},"end":{"line":34,"column":17,"offset":1053},"indent":[]}},{"type":"jsx","value":"<BasicImage width=\"280px\" src=\"https://res.cloudinary.com/dg3gyk0gu/image/upload/c_scale,w_260/v1589237755/maggieappleton.com/pure-react/PureRectMod_6_2x.png\" />","position":{"start":{"line":36,"column":1,"offset":1055},"end":{"line":36,"column":162,"offset":1216},"indent":[]}},{"type":"jsx","value":"<BasicImage width=\"280px\" src=\"https://res.cloudinary.com/dg3gyk0gu/image/upload/c_scale,w_260/v1589237755/maggieappleton.com/pure-react/PureRectMod_4_2x.png\" />","position":{"start":{"line":38,"column":1,"offset":1218},"end":{"line":38,"column":162,"offset":1379},"indent":[]}},{"type":"jsx","value":"<BasicImage width=\"280px\" src=\"https://res.cloudinary.com/dg3gyk0gu/image/upload/c_scale,w_260/v1589237755/maggieappleton.com/pure-react/PureRectMod_7_2x.png\" />","position":{"start":{"line":40,"column":1,"offset":1381},"end":{"line":40,"column":162,"offset":1542},"indent":[]}},{"type":"jsx","value":"<BasicImage width=\"280px\" src=\"https://res.cloudinary.com/dg3gyk0gu/image/upload/c_scale,w_260/v1589237755/maggieappleton.com/pure-react/PureRectMod_1_2x.png\" />","position":{"start":{"line":42,"column":1,"offset":1544},"end":{"line":42,"column":162,"offset":1705},"indent":[]}},{"type":"jsx","value":"<BasicImage width=\"280px\" src=\"https://res.cloudinary.com/dg3gyk0gu/image/upload/c_scale,w_260/v1589237755/maggieappleton.com/pure-react/PureRectMod_5_2x.png\" />","position":{"start":{"line":44,"column":1,"offset":1707},"end":{"line":44,"column":162,"offset":1868},"indent":[]}},{"type":"jsx","value":"<BasicImage width=\"280px\" src=\"https://res.cloudinary.com/dg3gyk0gu/image/upload/c_scale,w_260/v1589237755/maggieappleton.com/pure-react/PureRectMod_2_2x.png\" />","position":{"start":{"line":46,"column":1,"offset":1870},"end":{"line":46,"column":162,"offset":2031},"indent":[]}},{"type":"jsx","value":"</ThreeImageGrid>","position":{"start":{"line":48,"column":1,"offset":2033},"end":{"line":48,"column":18,"offset":2050},"indent":[]}},{"type":"jsx","value":"<br />","position":{"start":{"line":50,"column":1,"offset":2052},"end":{"line":50,"column":7,"offset":2058},"indent":[]}},{"type":"paragraph","children":[{"type":"text","value":"These show up on the landing page, and throughout the user interface once a learner is logged into the course site.","position":{"start":{"line":52,"column":1,"offset":2060},"end":{"line":52,"column":116,"offset":2175},"indent":[]}}],"position":{"start":{"line":52,"column":1,"offset":2060},"end":{"line":52,"column":116,"offset":2175},"indent":[]}},{"type":"jsx","value":"<BasicImage width=\"800px\" src=\"https://res.cloudinary.com/dg3gyk0gu/image/upload/v1589145522/maggieappleton.com/pure-react/PureReact_ModuleUI.png\" />","position":{"start":{"line":54,"column":1,"offset":2177},"end":{"line":54,"column":150,"offset":2326},"indent":[]}},{"type":"jsx","value":"<TwoCol>","position":{"start":{"line":56,"column":1,"offset":2328},"end":{"line":56,"column":9,"offset":2336},"indent":[]}},{"type":"paragraph","children":[{"type":"image","title":null,"url":"https://res.cloudinary.com/dg3gyk0gu/image/upload/v1589145524/maggieappleton.com/pure-react/Book-Small.png","alt":null,"position":{"start":{"line":58,"column":1,"offset":2338},"end":{"line":58,"column":112,"offset":2449},"indent":[]}}],"position":{"start":{"line":58,"column":1,"offset":2338},"end":{"line":58,"column":112,"offset":2449},"indent":[]}},{"type":"paragraph","children":[{"type":"text","value":"The course was built around a book Dave published a few years earlier. Since we were including the book in the expanded course material, it made sense to give it a design refresh and match the new style.","position":{"start":{"line":60,"column":1,"offset":2451},"end":{"line":60,"column":204,"offset":2654},"indent":[]}}],"position":{"start":{"line":60,"column":1,"offset":2451},"end":{"line":60,"column":204,"offset":2654},"indent":[]}},{"type":"jsx","value":"</TwoCol>","position":{"start":{"line":62,"column":1,"offset":2656},"end":{"line":62,"column":10,"offset":2665},"indent":[]}},{"type":"export","value":"export const _frontmatter = {\"slug\":\"pure-react\",\"updated\":\"2019-11-01T00:00:00.000Z\",\"title\":\"Pure React\",\"description\":null,\"published\":true,\"cover\":\"./purereactthumb.png\",\"type\":[\"illustration\"]}","position":{"start":{"line":66,"column":1,"offset":2669},"end":{"line":66,"column":199,"offset":2867},"indent":[]}}],"position":{"start":{"line":1,"column":1,"offset":0},"end":{"line":66,"column":199,"offset":2867}}},"scopeImports":["import * as React from 'react'"],"scopeIdentifiers":["React"],"body":"function _extends() { _extends = Object.assign || function (target) { for (var i = 1; i < arguments.length; i++) { var source = arguments[i]; for (var key in source) { if (Object.prototype.hasOwnProperty.call(source, key)) { target[key] = source[key]; } } } return target; }; return _extends.apply(this, arguments); }\n\nfunction _objectWithoutProperties(source, excluded) { if (source == null) return {}; var target = _objectWithoutPropertiesLoose(source, excluded); var key, i; if (Object.getOwnPropertySymbols) { var sourceSymbolKeys = Object.getOwnPropertySymbols(source); for (i = 0; i < sourceSymbolKeys.length; i++) { key = sourceSymbolKeys[i]; if (excluded.indexOf(key) >= 0) continue; if (!Object.prototype.propertyIsEnumerable.call(source, key)) continue; target[key] = source[key]; } } return target; }\n\nfunction _objectWithoutPropertiesLoose(source, excluded) { if (source == null) return {}; var target = {}; var sourceKeys = Object.keys(source); var key, i; for (i = 0; i < sourceKeys.length; i++) { key = sourceKeys[i]; if (excluded.indexOf(key) >= 0) continue; target[key] = source[key]; } return target; }\n\n/* @jsxRuntime classic */\n\n/* @jsx mdx */\nvar _frontmatter = {\n  \"slug\": \"pure-react\",\n  \"updated\": \"2019-11-01T00:00:00.000Z\",\n  \"title\": \"Pure React\",\n  \"description\": null,\n  \"published\": true,\n  \"cover\": \"./purereactthumb.png\",\n  \"type\": [\"illustration\"]\n};\n\nvar makeShortcode = function makeShortcode(name) {\n  return function MDXDefaultShortcode(props) {\n    console.warn(\"Component \" + name + \" was not imported, exported, or provided by MDXProvider as global scope\");\n    return mdx(\"div\", props);\n  };\n};\n\nvar FullWidthImage = makeShortcode(\"FullWidthImage\");\nvar Center = makeShortcode(\"Center\");\nvar BasicImage = makeShortcode(\"BasicImage\");\nvar FullWidth = makeShortcode(\"FullWidth\");\nvar ThreeImageGrid = makeShortcode(\"ThreeImageGrid\");\nvar TwoCol = makeShortcode(\"TwoCol\");\nvar layoutProps = {\n  _frontmatter: _frontmatter\n};\nvar MDXLayout = \"wrapper\";\nreturn function MDXContent(_ref) {\n  var components = _ref.components,\n      props = _objectWithoutProperties(_ref, [\"components\"]);\n\n  return mdx(MDXLayout, _extends({}, layoutProps, props, {\n    components: components,\n    mdxType: \"MDXLayout\"\n  }), mdx(FullWidthImage, {\n    src: \"https://res.cloudinary.com/dg3gyk0gu/image/upload/c_scale,w_1800/v1589145525/maggieappleton.com/pure-react/Cover.png\",\n    mdxType: \"FullWidthImage\"\n  }), mdx(Center, {\n    mdxType: \"Center\"\n  }, mdx(\"h2\", null, \"Illustration & art direction for Dave Ceddia's \", mdx(\"a\", {\n    noTip: true,\n    href: \"https://purereact.com/\"\n  }, \"Pure React\"), \" online course.\"), mdx(\"br\", null), mdx(\"br\", null), mdx(BasicImage, {\n    width: \"100px\",\n    src: \"https://res.cloudinary.com/dg3gyk0gu/image/upload/c_scale,w_100/v1589145522/maggieappleton.com/pure-react/PR_LogoLarge_2x.png\",\n    mdxType: \"BasicImage\"\n  })), mdx(\"br\", null), mdx(\"br\", null), mdx(FullWidth, {\n    bgcolour: \"linear-gradient(#09AFFD, #2F70E4)\",\n    mdxType: \"FullWidth\"\n  }, mdx(BasicImage, {\n    src: \"https://res.cloudinary.com/dg3gyk0gu/image/upload/c_scale,w_1000/v1589145523/maggieappleton.com/pure-react/Plant_Header.png\",\n    mdxType: \"BasicImage\"\n  })), mdx(\"br\", null), mdx(\"h2\", null, \"Module Illustrations\"), mdx(\"p\", null, \"The course is split into 9 modules, each focusing on a specific skill set like \", mdx(\"em\", {\n    parentName: \"p\"\n  }, \"Modern JavaScript Essentials\"), \", \", mdx(\"em\", {\n    parentName: \"p\"\n  }, \"API Requests,\"), \" and \", mdx(\"em\", {\n    parentName: \"p\"\n  }, \"Context for Application State\"), \". \"), mdx(\"p\", null, \"Each needed their own illustration, so I developed a unified shape language and colour palette to generate a variety of matching ones.\"), mdx(\"br\", null), mdx(ThreeImageGrid, {\n    mdxType: \"ThreeImageGrid\"\n  }, mdx(BasicImage, {\n    width: \"280px\",\n    src: \"https://res.cloudinary.com/dg3gyk0gu/image/upload/c_scale,w_260/v1589237755/maggieappleton.com/pure-react/PureRectMod_6_2x.png\",\n    mdxType: \"BasicImage\"\n  }), mdx(BasicImage, {\n    width: \"280px\",\n    src: \"https://res.cloudinary.com/dg3gyk0gu/image/upload/c_scale,w_260/v1589237755/maggieappleton.com/pure-react/PureRectMod_4_2x.png\",\n    mdxType: \"BasicImage\"\n  }), mdx(BasicImage, {\n    width: \"280px\",\n    src: \"https://res.cloudinary.com/dg3gyk0gu/image/upload/c_scale,w_260/v1589237755/maggieappleton.com/pure-react/PureRectMod_7_2x.png\",\n    mdxType: \"BasicImage\"\n  }), mdx(BasicImage, {\n    width: \"280px\",\n    src: \"https://res.cloudinary.com/dg3gyk0gu/image/upload/c_scale,w_260/v1589237755/maggieappleton.com/pure-react/PureRectMod_1_2x.png\",\n    mdxType: \"BasicImage\"\n  }), mdx(BasicImage, {\n    width: \"280px\",\n    src: \"https://res.cloudinary.com/dg3gyk0gu/image/upload/c_scale,w_260/v1589237755/maggieappleton.com/pure-react/PureRectMod_5_2x.png\",\n    mdxType: \"BasicImage\"\n  }), mdx(BasicImage, {\n    width: \"280px\",\n    src: \"https://res.cloudinary.com/dg3gyk0gu/image/upload/c_scale,w_260/v1589237755/maggieappleton.com/pure-react/PureRectMod_2_2x.png\",\n    mdxType: \"BasicImage\"\n  })), mdx(\"br\", null), mdx(\"p\", null, \"These show up on the landing page, and throughout the user interface once a learner is logged into the course site.\"), mdx(BasicImage, {\n    width: \"800px\",\n    src: \"https://res.cloudinary.com/dg3gyk0gu/image/upload/v1589145522/maggieappleton.com/pure-react/PureReact_ModuleUI.png\",\n    mdxType: \"BasicImage\"\n  }), mdx(TwoCol, {\n    mdxType: \"TwoCol\"\n  }, mdx(\"p\", null, mdx(\"img\", _extends({\n    parentName: \"p\"\n  }, {\n    \"src\": \"https://res.cloudinary.com/dg3gyk0gu/image/upload/v1589145524/maggieappleton.com/pure-react/Book-Small.png\",\n    \"alt\": null\n  }))), mdx(\"p\", null, \"The course was built around a book Dave published a few years earlier. Since we were including the book in the expanded course material, it made sense to give it a design refresh and match the new style.\")));\n}\n;\nMDXContent.isMDXComponent = true;","rawMDXOutput":"/* @jsx mdx */\nimport { mdx } from '@mdx-js/react';\n/* @jsxRuntime classic */\n/* @jsx mdx */\n\nexport const _frontmatter = {\n  \"slug\": \"pure-react\",\n  \"updated\": \"2019-11-01T00:00:00.000Z\",\n  \"title\": \"Pure React\",\n  \"description\": null,\n  \"published\": true,\n  \"cover\": \"./purereactthumb.png\",\n  \"type\": [\"illustration\"]\n};\nconst makeShortcode = name => function MDXDefaultShortcode(props) {\n      console.warn(\"Component \" + name + \" was not imported, exported, or provided by MDXProvider as global scope\")\n      return <div {...props}/>\n    };\nconst FullWidthImage = makeShortcode(\"FullWidthImage\");\nconst Center = makeShortcode(\"Center\");\nconst BasicImage = makeShortcode(\"BasicImage\");\nconst FullWidth = makeShortcode(\"FullWidth\");\nconst ThreeImageGrid = makeShortcode(\"ThreeImageGrid\");\nconst TwoCol = makeShortcode(\"TwoCol\");\nconst layoutProps = {\n  _frontmatter\n};\nconst MDXLayout = \"wrapper\"\nexport default function MDXContent({\n  components,\n  ...props\n}) {\n  return <MDXLayout {...layoutProps} {...props} components={components} mdxType=\"MDXLayout\">\n    <FullWidthImage src=\"https://res.cloudinary.com/dg3gyk0gu/image/upload/c_scale,w_1800/v1589145525/maggieappleton.com/pure-react/Cover.png\" mdxType=\"FullWidthImage\" />\n    <Center mdxType=\"Center\">\n      <h2>{`Illustration & art direction for Dave Ceddia's `}<a noTip href=\"https://purereact.com/\">{`Pure React`}</a>{` online course.`}</h2>\n      <br />\n      <br />\n      <BasicImage width=\"100px\" src=\"https://res.cloudinary.com/dg3gyk0gu/image/upload/c_scale,w_100/v1589145522/maggieappleton.com/pure-react/PR_LogoLarge_2x.png\" mdxType=\"BasicImage\" />\n    </Center>\n    <br />\n    <br />\n    <FullWidth bgcolour=\"linear-gradient(#09AFFD, #2F70E4)\" mdxType=\"FullWidth\">\n      <BasicImage src=\"https://res.cloudinary.com/dg3gyk0gu/image/upload/c_scale,w_1000/v1589145523/maggieappleton.com/pure-react/Plant_Header.png\" mdxType=\"BasicImage\" />\n    </FullWidth>\n    <br />\n    <h2>{`Module Illustrations`}</h2>\n    <p>{`The course is split into 9 modules, each focusing on a specific skill set like `}<em parentName=\"p\">{`Modern JavaScript Essentials`}</em>{`, `}<em parentName=\"p\">{`API Requests,`}</em>{` and `}<em parentName=\"p\">{`Context for Application State`}</em>{`. `}</p>\n    <p>{`Each needed their own illustration, so I developed a unified shape language and colour palette to generate a variety of matching ones.`}</p>\n    <br />\n    <ThreeImageGrid mdxType=\"ThreeImageGrid\">\n      <BasicImage width=\"280px\" src=\"https://res.cloudinary.com/dg3gyk0gu/image/upload/c_scale,w_260/v1589237755/maggieappleton.com/pure-react/PureRectMod_6_2x.png\" mdxType=\"BasicImage\" />\n      <BasicImage width=\"280px\" src=\"https://res.cloudinary.com/dg3gyk0gu/image/upload/c_scale,w_260/v1589237755/maggieappleton.com/pure-react/PureRectMod_4_2x.png\" mdxType=\"BasicImage\" />\n      <BasicImage width=\"280px\" src=\"https://res.cloudinary.com/dg3gyk0gu/image/upload/c_scale,w_260/v1589237755/maggieappleton.com/pure-react/PureRectMod_7_2x.png\" mdxType=\"BasicImage\" />\n      <BasicImage width=\"280px\" src=\"https://res.cloudinary.com/dg3gyk0gu/image/upload/c_scale,w_260/v1589237755/maggieappleton.com/pure-react/PureRectMod_1_2x.png\" mdxType=\"BasicImage\" />\n      <BasicImage width=\"280px\" src=\"https://res.cloudinary.com/dg3gyk0gu/image/upload/c_scale,w_260/v1589237755/maggieappleton.com/pure-react/PureRectMod_5_2x.png\" mdxType=\"BasicImage\" />\n      <BasicImage width=\"280px\" src=\"https://res.cloudinary.com/dg3gyk0gu/image/upload/c_scale,w_260/v1589237755/maggieappleton.com/pure-react/PureRectMod_2_2x.png\" mdxType=\"BasicImage\" />\n    </ThreeImageGrid>\n    <br />\n    <p>{`These show up on the landing page, and throughout the user interface once a learner is logged into the course site.`}</p>\n    <BasicImage width=\"800px\" src=\"https://res.cloudinary.com/dg3gyk0gu/image/upload/v1589145522/maggieappleton.com/pure-react/PureReact_ModuleUI.png\" mdxType=\"BasicImage\" />\n    <TwoCol mdxType=\"TwoCol\">\n      <p><img parentName=\"p\" {...{\n          \"src\": \"https://res.cloudinary.com/dg3gyk0gu/image/upload/v1589145524/maggieappleton.com/pure-react/Book-Small.png\",\n          \"alt\": null\n        }}></img></p>\n      <p>{`The course was built around a book Dave published a few years earlier. Since we were including the book in the expanded course material, it made sense to give it a design refresh and match the new style.`}</p>\n    </TwoCol>\n\n    </MDXLayout>;\n}\n\n;\nMDXContent.isMDXComponent = true;"}}