{"expireTime":9007200867590250000,"key":"f4f2fef61574d9564bf76fec26b227ac","val":{"name":"IMAGE_PROCESSING","inputPaths":["/Users/cyrus/Documents/GitHub/digital-garden/content/books/sweetness-power/sweetnesspower.jpg"],"outputDir":"/Users/cyrus/Documents/GitHub/digital-garden/public/static/510ca1f8afa48e718b3c94a7d88a502c","args":{"isLazy":false,"operations":[{"outputPath":"975bf/sweetnesspower.webp","args":{"width":225,"cropFocus":17,"toFormat":"webp","fit":"cover","background":"rgba(0,0,0,1)"}},{"outputPath":"53cab/sweetnesspower.webp","args":{"width":308,"cropFocus":17,"toFormat":"webp","fit":"cover","background":"rgba(0,0,0,1)"}}],"pluginOptions":{"base64Width":20,"forceBase64Format":"","useMozJpeg":false,"stripMetadata":true,"lazyImageGeneration":true,"defaultQuality":50,"failOnError":true,"plugins":[]}}}}